hello_world_sandhya/app.py
hello_world_sandhya-1.0.4.dist-info/LICENSE
hello_world_sandhya-1.0.4.dist-info/METADATA
hello_world_sandhya-1.0.4.dist-info/WHEEL
hello_world_sandhya-1.0.4.dist-info/entry_points.txt
hello_world_sandhya-1.0.4.dist-info/top_level.txt
hello_world_sandhya-1.0.4.dist-info/RECORD
