Metadata-Version: 2.1
Name: hello-world-sandhya
Version: 1.0.4
Summary: A Python package to get say hello to everyone
Home-page: https://github.com/sandmadh/projectWork
Author: Sandhya Mulay
Author-email: sandhya.mulay20@gmail.com
License: MIT
Platform: UNKNOWN
Classifier: License :: OSI Approved :: MIT License
Classifier: Programming Language :: Python :: 3
Classifier: Programming Language :: Python :: 3.7
